getcodium/__init__.py
getcodium/codium.mirrors
getcodium/getcodium.sh
getcodium-0.0.4.dist-info/METADATA
getcodium-0.0.4.dist-info/WHEEL
getcodium-0.0.4.dist-info/entry_points.txt
getcodium-0.0.4.dist-info/top_level.txt
getcodium-0.0.4.dist-info/RECORD
