Metadata-Version: 2.1
Name: getcodium
Version: 0.0.4
Summary: getcodium
Home-page: https://github.com/larryw3i/getcodium
Author: larryw3i & Contributors
Author-email: 
License: UNKNOWN
Platform: UNKNOWN
Classifier: Programming Language :: Python :: 3
Classifier: License :: OSI Approved :: MIT License
Classifier: Operating System :: OS Independent
Requires-Python: >=3.6
